{
  "$schema": "https://raw.githubusercontent.com/jsonresume/resume-schema/v1.0.0/schema.json",
  "meta": {
    "canonical": "https://greenmatchers.in/resume/5",
    "version": "v1.0.0",
    "lastModified": "2026-02-01T16:52:14.109511"
  },
  "basics": {
    "name": "Ananya Chatterjee",
    "label": "Waste Management Specialist",
    "email": "ananya.c@email.com",
    "phone": "+91 98765 11111",
    "summary": "Environmental engineer with 6 years in solid waste management and recycling. Expertise in waste-to-energy projects. Committed to circular economy principles.",
    "location": {
      "city": "Kolkata",
      "countryCode": "IN",
      "region": "West Bengal"
    },
    "profiles": []
  },
  "work": [
    {
      "name": "Ramky Enviro Engineers",
      "position": "Waste Management Specialist",
      "location": "Kolkata",
      "startDate": "2021-04",
      "endDate": "",
      "summary": "Green jobs experience in waste management specialist",
      "highlights": [
        "Designed waste segregation programs for 5 municipalities",
        "Managed waste-to-energy plant (15 TPD capacity)",
        "Reduced landfill waste by 40%",
        "Trained 200+ waste collection workers"
      ]
    }
  ],
  "education": [
    {
      "institution": "Jadavpur University",
      "area": "B.Tech Environmental Engineering",
      "studyType": "Bachelors",
      "startDate": "",
      "endDate": "2018",
      "gpa": ""
    }
  ],
  "skills": [
    {
      "name": "Environmental & Sustainability",
      "level": "Advanced",
      "keywords": [
        "Solid waste management",
        "Waste-to-energy systems",
        "Composting and recycling",
        "Environmental impact assessment"
      ]
    },
    {
      "name": "Management & Leadership",
      "level": "Advanced",
      "keywords": [
        "Project management"
      ]
    },
    {
      "name": "Other Skills",
      "level": "Advanced",
      "keywords": [
        "GIS mapping"
      ]
    }
  ],
  "languages": [
    {
      "language": "Bengali",
      "fluency": "Native speaker"
    },
    {
      "language": "English",
      "fluency": "Conversational"
    }
  ],
  "interests": [
    {
      "name": "Sustainability",
      "keywords": [
        "Green Energy",
        "Environmental Conservation",
        "Climate Action"
      ]
    }
  ],
  "certificates": [
    {
      "name": "Certified Waste Management Professional",
      "date": "",
      "issuer": "Professional Organization"
    },
    {
      "name": "Hazardous Waste Management Training",
      "date": "",
      "issuer": "Professional Organization"
    }
  ]
}